evdevUtils/__init__.py
evdevUtils/enums.py
evdevUtils/listener.py
totoBotKey/__init__.py
totoBotKey/buttons.py
totoBotKey/commands.py
totoBotKey/commandsraw.py
totoBotKey/decorators.py
totoBotKey/enums.py
totoBotKey/inputs.py
totoBotKey/keys.py
totoBotKey/parser.py
totoBotKey/runtime.py
ydotoolUtils/__init__.py
ydotoolUtils/ydotool.py
ydotoolUtils/ydotoold.py
totobotkey-0.0.6.dist-info/METADATA
totobotkey-0.0.6.dist-info/WHEEL
totobotkey-0.0.6.dist-info/top_level.txt
totobotkey-0.0.6.dist-info/RECORD
