Metadata-Version: 2.4
Name: TotoBotKey
Version: 0.0.6
Summary: Just like AutoHotKey, on Wayland (and probably X)
Author-email: Vanane <vanane@vanane.net>
Project-URL: homepage, https://github.com/Vanane/TotoBotKey/tree/main/src/TotoBotKey
Project-URL: issues, https://github.com/Vanane/TotoBotKey/issues?q=label%3Atotobotkey
Keywords: Automation,Wayland,Macro
Classifier: Operating System :: POSIX :: Linux
Classifier: Programming Language :: Python :: 3
Classifier: Topic :: Desktop Environment
Requires-Python: >=3.12
Requires-Dist: evdev>=1.7.1
Requires-Dist: bitstring>=4.2.3
Requires-Dist: setuptools>=75.0
